nimbuscfg/__init__.py
nimbuscfg/config.py
nimbuscfg/nimbus.conf
nimbuscfg/prompts.py
nimbuscfg/stanzas.py
nimbuscfg/init.d/nimbus.debian
nimbuscfg/init.d/tunnel.debian
nimbusdrivers/__init__.py
nimbusdrivers/acurite.py
nimbusdrivers/cc3000.py
nimbusdrivers/fousb.py
nimbusdrivers/simulator.py
nimbusdrivers/te923.py
nimbusdrivers/ultimeter.py
nimbusdrivers/vantage.py
nimbusdrivers/wmr100.py
nimbusdrivers/wmr200.py
nimbusdrivers/wmr9x8.py
nimbusdrivers/ws1.py
nimbusdrivers/ws23xx.py
nimbusdrivers/ws28xx.py
nimbusmain/__init__.py
nimbusmain/accum.py
nimbusmain/engine.py
nimbusmain/formulas.py
nimbusmain/rest.py
nimbusmain/services.py
nimbusmain/units.py
nimbusmain/util.py
nimbusweather-1.0.36.data/scripts/nimbus
nimbusweather-1.0.36.data/scripts/nimbus_config
nimbusweather-1.0.36.dist-info/LICENSE.txt
nimbusweather-1.0.36.dist-info/METADATA
nimbusweather-1.0.36.dist-info/WHEEL
nimbusweather-1.0.36.dist-info/namespace_packages.txt
nimbusweather-1.0.36.dist-info/top_level.txt
nimbusweather-1.0.36.dist-info/zip-safe
nimbusweather-1.0.36.dist-info/RECORD
